aiocfscrape/__init__.py
aiocfscrape-0.0.6.dist-info/METADATA
aiocfscrape-0.0.6.dist-info/RECORD
aiocfscrape-0.0.6.dist-info/WHEEL
aiocfscrape-0.0.6.dist-info/top_level.txt
