Metadata-Version: 2.1
Name: aiocfscrape
Version: 0.0.6
Summary: A simple async Python module to bypass Cloudflare's anti-bot page. See https://github.com/pavlodvornikov/aiocfscrape for more information.
Home-page: https://github.com/pavlodvornikov/aiocfscrape
Author: pavlodvornikov
Author-email: pavlodvornikov@gmail.com
License: UNKNOWN
Keywords: cloudflare,scraping,asyncio
Platform: UNKNOWN
Requires-Dist: js2py (==0.59)
Requires-Dist: aiohttp (>=3.1.3)
